gender/__init__.py
gender/gender.py
gender/data/data_grammgender_.json
gender/data/data_hypocorisms_.json
gender/data/data_last_names_.txt
gender/data/data_names_.json
gender/data/data_salutations_.json
gender/data/jnames.json
gender-0.0.33.dist-info/LICENSE
gender-0.0.33.dist-info/METADATA
gender-0.0.33.dist-info/WHEEL
gender-0.0.33.dist-info/top_level.txt
gender-0.0.33.dist-info/RECORD
