Metadata-Version: 2.1
Name: gender
Version: 0.0.33
Summary: Get gender from name and email address
Home-page: https://github.com/eeghor/gender
Author: Igor Korostil
Author-email: eeghor@gmail.com
License: MIT
Keywords: gender name email
Platform: UNKNOWN
Classifier: Development Status :: 3 - Alpha
Classifier: Programming Language :: Python :: 3.8
Classifier: Topic :: Text Processing
Classifier: Topic :: Text Processing :: Filters
Requires-Python: >=3.8
License-File: LICENSE
Requires-Dist: unidecode
